{
  "kind": "youtube#searchResult",
  "etag": "lgcXqddv2xaoNKyNTLP02fJ9L4s",
  "id": {
    "kind": "youtube#video",
    "videoId": "IZXR238UyR0"
  },
  "snippet": {
    "publishedAt": "2019-10-30T16:00:02Z",
    "channelId": "UCFQ6Gptuq-sLflbJ4YY3Umw",
    "title": "Rebel Wisdom on tour! Washington DC &amp; Toronto",
    "description": "Rebel Wisdom on tour! Washington DC Meetup with RW founder David Fuller on Monday 4th November - register here: ...",
    "thumbnails": {
      "default": {
        "url": "https://i.ytimg.com/vi/IZXR238UyR0/default.jpg",
        "width": 120,
        "height": 90
      },
      "medium": {
        "url": "https://i.ytimg.com/vi/IZXR238UyR0/mqdefault.jpg",
        "width": 320,
        "height": 180
      },
      "high": {
        "url": "https://i.ytimg.com/vi/IZXR238UyR0/hqdefault.jpg",
        "width": 480,
        "height": 360
      }
    },
    "channelTitle": "Rebel Wisdom",
    "liveBroadcastContent": "none",
    "publishTime": "2019-10-30T16:00:02Z"
  },
  "_id": "IZXR238UyR0",
  "collections": [
    "https://www.youtube.com/channel/UCFQ6Gptuq-sLflbJ4YY3Umw"
  ]
}