{
  "kind": "youtube#searchResult",
  "etag": "lucpTR1XeOx3E-HfKFJ4-vbxwio",
  "id": {
    "kind": "youtube#video",
    "videoId": "kKUaxjkNzb8"
  },
  "snippet": {
    "publishedAt": "2020-04-13T11:30:15Z",
    "channelId": "UCN06e1C9M4mMffP5OIgTJtg",
    "title": "In the Beginning",
    "description": "My contribution to the digital campfire. From a forthcoming album of songs based on the first book of Genesis. Lyrics: In the beginning In the beginning There ...",
    "thumbnails": {
      "default": {
        "url": "https://i.ytimg.com/vi/kKUaxjkNzb8/default.jpg",
        "width": 120,
        "height": 90
      },
      "medium": {
        "url": "https://i.ytimg.com/vi/kKUaxjkNzb8/mqdefault.jpg",
        "width": 320,
        "height": 180
      },
      "high": {
        "url": "https://i.ytimg.com/vi/kKUaxjkNzb8/hqdefault.jpg",
        "width": 480,
        "height": 360
      }
    },
    "channelTitle": "Andrew Sweeny",
    "liveBroadcastContent": "none",
    "publishTime": "2020-04-13T11:30:15Z"
  },
  "_id": "kKUaxjkNzb8",
  "collections": [
    "https://www.youtube.com/channel/UCN06e1C9M4mMffP5OIgTJtg"
  ]
}