{
  "kind": "youtube#searchResult",
  "etag": "ZGmsCX14UmUE9EkRyU3vnLScvj8",
  "id": {
    "kind": "youtube#video",
    "videoId": "XmRsgkiuVps"
  },
  "snippet": {
    "publishedAt": "2017-07-20T10:16:13Z",
    "channelId": "UCV-EEU6aLT7SSJegb453hOw",
    "title": "ZEITGEIST ll - THE ADDENDUM",
    "description": "For me this is the single most powerful and influential film of its type I have seen. Superbly made and narrated, enhanced with clips, voices and contributions ...",
    "thumbnails": {
      "default": {
        "url": "https://i.ytimg.com/vi/XmRsgkiuVps/default.jpg",
        "width": 120,
        "height": 90
      },
      "medium": {
        "url": "https://i.ytimg.com/vi/XmRsgkiuVps/mqdefault.jpg",
        "width": 320,
        "height": 180
      },
      "high": {
        "url": "https://i.ytimg.com/vi/XmRsgkiuVps/hqdefault.jpg",
        "width": 480,
        "height": 360
      }
    },
    "channelTitle": "liberatemankind",
    "liveBroadcastContent": "none",
    "publishTime": "2017-07-20T10:16:13Z"
  }
}