{
  "kind": "youtube#searchResult",
  "etag": "yhYqHSDhtRpk64pF_QGEp7QPp2M",
  "id": {
    "kind": "youtube#video",
    "videoId": "YYBYsd9gS2I"
  },
  "snippet": {
    "publishedAt": "2017-07-20T10:15:17Z",
    "channelId": "UCV-EEU6aLT7SSJegb453hOw",
    "title": "ZEITGEIST",
    "description": "This is the first of the 3 Zeitgeist films. Topics covered include religion, false flag attacks and the monetary system. The religion section has been widely ...",
    "thumbnails": {
      "default": {
        "url": "https://i.ytimg.com/vi/YYBYsd9gS2I/default.jpg",
        "width": 120,
        "height": 90
      },
      "medium": {
        "url": "https://i.ytimg.com/vi/YYBYsd9gS2I/mqdefault.jpg",
        "width": 320,
        "height": 180
      },
      "high": {
        "url": "https://i.ytimg.com/vi/YYBYsd9gS2I/hqdefault.jpg",
        "width": 480,
        "height": 360
      }
    },
    "channelTitle": "liberatemankind",
    "liveBroadcastContent": "none",
    "publishTime": "2017-07-20T10:15:17Z"
  }
}