{
  "kind": "youtube#playlistItem",
  "etag": "qNqPS5RUtBC7e5IMRw0YSrMXFGA",
  "id": "UExwUkVoRzdHdGp0Q2g5MFFyem5NUFhTN0J4aDNMVW5QVi41QUZGQTY5OTE4QTREQUU4",
  "snippet": {
    "publishedAt": "2019-08-05T22:07:00Z",
    "channelId": "UCPXPLSHHQIrQY3_vFsonXXA",
    "title": "Jordan Greenhall - Complexity in Governance",
    "description": "Government Futures Lab, Reconstitutional Convention\nJordan Greenhall",
    "thumbnails": {
      "default": {
        "url": "https://i.ytimg.com/vi/I2DAjjS0rcM/default.jpg",
        "width": 120,
        "height": 90
      },
      "medium": {
        "url": "https://i.ytimg.com/vi/I2DAjjS0rcM/mqdefault.jpg",
        "width": 320,
        "height": 180
      },
      "high": {
        "url": "https://i.ytimg.com/vi/I2DAjjS0rcM/hqdefault.jpg",
        "width": 480,
        "height": 360
      },
      "standard": {
        "url": "https://i.ytimg.com/vi/I2DAjjS0rcM/sddefault.jpg",
        "width": 640,
        "height": 480
      },
      "maxres": {
        "url": "https://i.ytimg.com/vi/I2DAjjS0rcM/maxresdefault.jpg",
        "width": 1280,
        "height": 720
      }
    },
    "channelTitle": "Gwendolyn Huot",
    "playlistId": "PLpREhG7GtjtCh90QrznMPXS7Bxh3LUnPV",
    "position": 0,
    "resourceId": {
      "kind": "youtube#video",
      "videoId": "I2DAjjS0rcM"
    }
  }
}