{
  "kind": "youtube#searchResult",
  "etag": "faVZ2YmQFFdZGd4R9-zAnYsOQmU",
  "id": {
    "kind": "youtube#video",
    "videoId": "4pE4gFfy8Do"
  },
  "snippet": {
    "publishedAt": "2018-07-23T14:32:33Z",
    "channelId": "UCFQ6Gptuq-sLflbJ4YY3Umw",
    "title": "First Rebel Wisdom QnA - questions please!",
    "description": "First Rebel Wisdom QnA - questions please! On Thursday, David and Alexander will host the first Rebel Wisdom QnA. Please ask questions in the comments ...",
    "thumbnails": {
      "default": {
        "url": "https://i.ytimg.com/vi/4pE4gFfy8Do/default.jpg",
        "width": 120,
        "height": 90
      },
      "medium": {
        "url": "https://i.ytimg.com/vi/4pE4gFfy8Do/mqdefault.jpg",
        "width": 320,
        "height": 180
      },
      "high": {
        "url": "https://i.ytimg.com/vi/4pE4gFfy8Do/hqdefault.jpg",
        "width": 480,
        "height": 360
      }
    },
    "channelTitle": "Rebel Wisdom",
    "liveBroadcastContent": "none",
    "publishTime": "2018-07-23T14:32:33Z"
  },
  "_id": "4pE4gFfy8Do",
  "collections": [
    "https://www.youtube.com/channel/UCFQ6Gptuq-sLflbJ4YY3Umw"
  ]
}