{
  "kind": "youtube#searchResult",
  "etag": "g6ePiUix_qaP4mWkq4ljnZDfWgQ",
  "id": {
    "kind": "youtube#video",
    "videoId": "97EFRsWadYk"
  },
  "snippet": {
    "publishedAt": "2020-03-31T03:35:28Z",
    "channelId": "UCfI5jzpoUbwP4wkmQ6ZNqbA",
    "title": "Overcoming Bias During COVID-19: Considering Deliberate Infection w/ Robin Hanson",
    "description": "Robin Hanson will be sharing his thoughts on COVID-19, focusing on deliberate infection. Optional reading: ...",
    "thumbnails": {
      "default": {
        "url": "https://i.ytimg.com/vi/97EFRsWadYk/default.jpg",
        "width": 120,
        "height": 90
      },
      "medium": {
        "url": "https://i.ytimg.com/vi/97EFRsWadYk/mqdefault.jpg",
        "width": 320,
        "height": 180
      },
      "high": {
        "url": "https://i.ytimg.com/vi/97EFRsWadYk/hqdefault.jpg",
        "width": 480,
        "height": 360
      }
    },
    "channelTitle": "The Stoa",
    "liveBroadcastContent": "none",
    "publishTime": "2020-03-31T03:35:28Z"
  },
  "_id": "97EFRsWadYk",
  "collections": [
    "https://www.youtube.com/channel/UCfI5jzpoUbwP4wkmQ6ZNqbA"
  ]
}